omics/__init__.py
omics/cli/__init__.py
omics/cli/rerun/__init__.py
omics/cli/rerun/__main__.py
omics/cli/run_analyzer/__init__.py
omics/cli/run_analyzer/__main__.py
omics/cli/run_analyzer/batch.py
omics/cli/run_analyzer/timeline.py
omics/cli/run_analyzer/utils.py
omics/cli/run_analyzer/writeconfig.py
omics/common/__init__.py
omics/common/omics_file_types.py
omics/transfer/__init__.py
omics/transfer/config.py
omics/transfer/download.py
omics/transfer/manager.py
omics/transfer/read_set_upload.py
omics/uriparse/__init__.py
omics/uriparse/uri_parse.py
amazon_omics_tools-0.10.0.dist-info/LICENSE
amazon_omics_tools-0.10.0.dist-info/METADATA
amazon_omics_tools-0.10.0.dist-info/NOTICE
amazon_omics_tools-0.10.0.dist-info/WHEEL
amazon_omics_tools-0.10.0.dist-info/RECORD
